rats/__init__.py
rats/modeling_CCF.py
rats/modeling_CCF_lists.py
rats/modeling_RM_CLV.py
rats/ndarray_utilities.py
rats/orbital_functions.py
rats/parameters.py
rats/parameters_old.py
rats/photometry.py
rats/plot_functions.py
rats/plot_spectra.py
rats/plot_spectra_animations.py
rats/plot_utilities.py
rats/run_molecfit_all.py
rats/single_use.py
rats/spectra_cross_correlate.py
rats/spectra_loaders.py
rats/spectra_manipulation.py
rats/spectra_modeling.py
rats/table.py
rats/template_transmission_spectroscopy.py
rats/utilities.py
rats_transmission-0.3.1.dist-info/LICENSE
rats_transmission-0.3.1.dist-info/METADATA
rats_transmission-0.3.1.dist-info/WHEEL
rats_transmission-0.3.1.dist-info/top_level.txt
rats_transmission-0.3.1.dist-info/RECORD
