Metadata-Version: 2.1
Name: rats-transmission
Version: 0.3.1
Summary: Revealing Atmospheres with Transmission Spectroscopy
Author-email: Michal Steiner <michal.steiner@unige.ch>
Project-URL: Homepage, https://github.com/MichalSteiner/rats
Project-URL: Issues, https://github.com/MichalSteiner/rats/issues
Classifier: Programming Language :: Python :: 3
Classifier: License :: OSI Approved :: GNU General Public License v3 or later (GPLv3+)
Classifier: Operating System :: OS Independent
Requires-Python: >=3.10
License-File: LICENSE
